tdgl/__init__.py
tdgl/about.py
tdgl/distance.py
tdgl/em.py
tdgl/fluxoid.py
tdgl/geometry.py
tdgl/parameter.py
tdgl/testing.py
tdgl/version.py
tdgl/visualize.py
tdgl/device/__init__.py
tdgl/device/device.py
tdgl/device/layer.py
tdgl/device/meshing.py
tdgl/device/polygon.py
tdgl/finite_volume/__init__.py
tdgl/finite_volume/edge_mesh.py
tdgl/finite_volume/mesh.py
tdgl/finite_volume/operators.py
tdgl/finite_volume/util.py
tdgl/solution/__init__.py
tdgl/solution/data.py
tdgl/solution/plot_solution.py
tdgl/solution/solution.py
tdgl/solver/__init__.py
tdgl/solver/options.py
tdgl/solver/runner.py
tdgl/solver/screening.py
tdgl/solver/solve.py
tdgl/solver/solver.py
tdgl/sources/__init__.py
tdgl/sources/constant.py
tdgl/sources/loop.py
tdgl/sources/scaling.py
tdgl/test/__init__.py
tdgl/test/conftest.py
tdgl/test/test_about.py
tdgl/test/test_device.py
tdgl/test/test_distance.py
tdgl/test/test_em.py
tdgl/test/test_parameter.py
tdgl/test/test_solution.py
tdgl/test/test_solve.py
tdgl/test/test_visualization.py
tdgl/test/test_visualize.py
tdgl/visualization/__init__.py
tdgl/visualization/animate.py
tdgl/visualization/common.py
tdgl/visualization/convert.py
tdgl/visualization/interactive.py
tdgl/visualization/io.py
tdgl/visualization/monitor.py
tdgl/visualization/snapshot.py
tdgl-0.8.4.dist-info/licenses/LICENSE
tdgl-0.8.4.dist-info/METADATA
tdgl-0.8.4.dist-info/WHEEL
tdgl-0.8.4.dist-info/top_level.txt
tdgl-0.8.4.dist-info/RECORD
