Metadata-Version: 2.4
Name: tdgl
Version: 0.8.4
Summary: pyTDGL: Time-dependent Ginzburg-Landau in Python.
Home-page: https://github.com/loganbvh/py-tdgl
Author: Logan Bishop-Van Horn
Author-email: logan.bvh@gmail.com
License: MIT
Keywords: superconductor vortex Ginzburg-Landau
Platform: Linux
Platform: Mac OSX
Platform: Unix
Platform: Windows
Classifier: Development Status :: 3 - Alpha
Classifier: Intended Audience :: Science/Research
Classifier: License :: OSI Approved :: MIT License
Classifier: Operating System :: MacOS
Classifier: Operating System :: POSIX
Classifier: Operating System :: Unix
Classifier: Operating System :: Microsoft :: Windows
Classifier: Programming Language :: Python
Classifier: Programming Language :: Python :: 3.8
Classifier: Programming Language :: Python :: 3.9
Classifier: Programming Language :: Python :: 3.10
Classifier: Programming Language :: Python :: 3.11
Classifier: Programming Language :: Python :: 3.12
Classifier: Programming Language :: Python :: 3.13
Classifier: Programming Language :: Python :: 3.14
Classifier: Intended Audience :: Science/Research
Classifier: Topic :: Scientific/Engineering
Classifier: Topic :: Scientific/Engineering :: Physics
Requires-Python: >=3.8, <3.15
License-File: LICENSE
Requires-Dist: cloudpickle
Requires-Dist: h5py
Requires-Dist: joblib
Requires-Dist: jupyter
Requires-Dist: matplotlib
Requires-Dist: meshpy
Requires-Dist: numba
Requires-Dist: numpy
Requires-Dist: pint
Requires-Dist: pytest
Requires-Dist: pytest-cov
Requires-Dist: scipy
Requires-Dist: shapely
Requires-Dist: tqdm
Provides-Extra: dev
Requires-Dist: black; extra == "dev"
Requires-Dist: isort; extra == "dev"
Requires-Dist: pre-commit; extra == "dev"
Provides-Extra: docs
Requires-Dist: IPython; extra == "docs"
Requires-Dist: sphinx==5.3.0; extra == "docs"
Requires-Dist: sphinx-rtd-theme>=0.5.2; extra == "docs"
Requires-Dist: sphinx-autodoc-typehints; extra == "docs"
Requires-Dist: nbsphinx; extra == "docs"
Requires-Dist: pillow; extra == "docs"
Requires-Dist: sphinx_toolbox; extra == "docs"
Requires-Dist: enum_tools; extra == "docs"
Requires-Dist: sphinx-argparse; extra == "docs"
Requires-Dist: sphinxcontrib-bibtex; extra == "docs"
Provides-Extra: umfpack
Requires-Dist: swig; extra == "umfpack"
Requires-Dist: scikit-umfpack; extra == "umfpack"
Provides-Extra: pardiso
Requires-Dist: pypardiso; extra == "pardiso"
Dynamic: author
Dynamic: author-email
Dynamic: classifier
Dynamic: description
Dynamic: description-content-type
Dynamic: home-page
Dynamic: keywords
Dynamic: license
Dynamic: license-file
Dynamic: platform
Dynamic: provides-extra
Dynamic: requires-dist
Dynamic: requires-python
Dynamic: summary
